jupyterlab_broccoli/__init__.py
jupyterlab_broccoli/_version.py
jupyterlab_broccoli/labextension/build_log.json
jupyterlab_broccoli/labextension/package.json
jupyterlab_broccoli/labextension/static/blockly_lib_index_js.5945d026d86ac236a218.js
jupyterlab_broccoli/labextension/static/blockly_lib_index_js.5945d026d86ac236a218.js.map
jupyterlab_broccoli/labextension/static/blockly_lib_msg_En_js.9620c25a3e65873673e0.js
jupyterlab_broccoli/labextension/static/blockly_lib_msg_En_js.9620c25a3e65873673e0.js.map
jupyterlab_broccoli/labextension/static/blockly_lib_msg_Jp_js.ada59de1741510cb7077.js
jupyterlab_broccoli/labextension/static/blockly_lib_msg_Jp_js.ada59de1741510cb7077.js.map
jupyterlab_broccoli/labextension/static/lib_index_js.df422f06fa7463096c4d.js
jupyterlab_broccoli/labextension/static/lib_index_js.df422f06fa7463096c4d.js.map
jupyterlab_broccoli/labextension/static/remoteEntry.c13681faf26b64289be7.js
jupyterlab_broccoli/labextension/static/remoteEntry.c13681faf26b64289be7.js.map
jupyterlab_broccoli/labextension/static/style.js
jupyterlab_broccoli/labextension/static/style_index_js.44926c868e08551b4628.js
jupyterlab_broccoli/labextension/static/style_index_js.44926c868e08551b4628.js.map
jupyterlab_broccoli/labextension/static/vendors-node_modules_blockly_index_js.dfb1c5e9eee06041c9d8.js
jupyterlab_broccoli/labextension/static/vendors-node_modules_blockly_index_js.dfb1c5e9eee06041c9d8.js.map
jupyterlab_broccoli/labextension/static/vendors-node_modules_blockly_javascript_js-node_modules_blockly_msg_en_js.b27579ddbcb26b7f4deb.js
jupyterlab_broccoli/labextension/static/vendors-node_modules_blockly_javascript_js-node_modules_blockly_msg_en_js.b27579ddbcb26b7f4deb.js.map
jupyterlab_broccoli/labextension/static/vendors-node_modules_blockly_msg_ar_js.8cc58c14d37b8570395d.js
jupyterlab_broccoli/labextension/static/vendors-node_modules_blockly_msg_ar_js.8cc58c14d37b8570395d.js.map
jupyterlab_broccoli-0.4.7.dist-info/METADATA
jupyterlab_broccoli-0.4.7.dist-info/WHEEL
jupyterlab_broccoli-0.4.7.dist-info/licenses/LICENSE
jupyterlab_broccoli-0.4.7.dist-info/RECORD
