Metadata-Version: 2.3
Name: jupyterlab_broccoli
Version: 0.4.7
Dynamic: Keywords
Summary: Fork of blockly extension for JupyterLab.
Project-URL: Homepage, https://github.com/FumiHax/jupyterlab-broccoli
Project-URL: Bug Tracker, https://github.com/FumiHax/jupyterlab-broccoli/issues
Project-URL: Repository, https://github.com/FumiHax/jupyterlab-broccoli.git
Author-email: "Fumi.Iseki" <iseki@rsch.tuis.ac.jp>
License: BSD 3-Clause License
License-File: LICENSE
Classifier: Framework :: Jupyter
Classifier: Framework :: Jupyter :: JupyterLab
Classifier: Framework :: Jupyter :: JupyterLab :: 3
Classifier: Framework :: Jupyter :: JupyterLab :: Extensions
Classifier: Framework :: Jupyter :: JupyterLab :: Extensions :: Prebuilt
Classifier: License :: OSI Approved :: BSD License
Classifier: Programming Language :: Python
Classifier: Programming Language :: Python :: 3
Classifier: Programming Language :: Python :: 3.7
Classifier: Programming Language :: Python :: 3.8
Classifier: Programming Language :: Python :: 3.9
Classifier: Programming Language :: Python :: 3.10
Classifier: Programming Language :: Python :: 3.11
Requires-Python: >=3.7
Requires-Dist: jupyterlab>=4.1
Provides-Extra: dev
Requires-Dist: click; extra == 'dev'
Requires-Dist: jupyter-releaser; extra == 'dev'
Requires-Dist: pre-commit; extra == 'dev'
